keras_remote/__init__.py
keras_remote/core.py
keras_remote/infra.py
keras_remote/packager.py
keras_remote/remote_runner.py
keras_remote-0.0.1.dist-info/METADATA
keras_remote-0.0.1.dist-info/WHEEL
keras_remote-0.0.1.dist-info/RECORD
