Metadata-Version: 2.4
Name: keras-remote
Version: 0.0.1
Summary: Run Keras models remotely on TPU seamlessly.
Project-URL: Homepage, https://github.com/keras-team/keras-remote
Project-URL: Issues, https://github.com/keras-team/keras-remote/issues
Author-email: Jeff Carpenter <code@jeffcarp.com>
License-Expression: Apache-2.0
Classifier: Operating System :: OS Independent
Classifier: Programming Language :: Python :: 3
Requires-Python: >=3.9
Requires-Dist: cloudpickle
Requires-Dist: keras
Requires-Dist: numpy
Provides-Extra: dev
Requires-Dist: build; extra == 'dev'
Requires-Dist: twine; extra == 'dev'
